LICENSE
MANIFEST.in
README.rst
categorytpl.py
setup.py
test_categorytpl.py
pelican_category_template.egg-info/PKG-INFO
pelican_category_template.egg-info/SOURCES.txt
pelican_category_template.egg-info/dependency_links.txt
pelican_category_template.egg-info/requires.txt
pelican_category_template.egg-info/top_level.txt