Metadata-Version: 1.1
Name: pelican-category-template
Version: v0.0.2
Summary: A pelican plugin to apply a template based on the category of the content.
Home-page: https://github.com/hrbonz/pelican-category_template
Author: Stefan "hr" Berder
Author-email: hr@bonz.org
License: BSD 2-Clause
Platform: UNKNOWN
Classifier: Development Status :: 6 - Mature
Classifier: Environment :: Console
Classifier: Intended Audience :: Developers
Classifier: License :: OSI Approved :: BSD License
Classifier: Topic :: Internet
